# 无锁并发

- CAS 与 volatile （CAS + volatile 实现无锁并发）
- 原子整数 
- 原子引用 
- 原子累加器 
- Unsafe：提供了 CAS 底层的访问接口

# 问题

有如下需求，保证 account.withdraw 取款方法的线程安全

```java
package unlock;

import java.util.ArrayList;
import java.util.List;

public class TestAccount {
    public static void main(String[] args) {
        Account account = new AccountUnsafe(10000);
        Account.demo(account);
    }
}

class AccountUnsafe implements Account {
    private Integer balance;

    public AccountUnsafe(Integer balance) {
        this.balance = balance;
    }

    @Override
    public Integer getBalance() {
        return balance;
    }

    @Override
    public void withdraw(Integer amount) {
        this.balance -= amount;
    }
}

interface Account {
    // 获取余额
    Integer getBalance();

    // 取款
    void withdraw(Integer amount);

    /**
     * 方法内会启动 1000 个线程，每个线程做 -10 元 的操作
     * 如果初始余额为 10000 那么正确的结果应当是 0
     */
    static void demo(Account account) {
        List<Thread> ts = new ArrayList<>();
        long start = System.nanoTime();
        for (int i = 0; i < 1000; i++) {
            ts.add(new Thread(() -> {
                account.withdraw(10);
            }));
        }
        ts.forEach(Thread::start);
        ts.forEach(t -> {
            try {
                t.join();
            } catch (InterruptedException e) {
                e.printStackTrace();
            }
        });
        long end = System.nanoTime();
        System.out.println(account.getBalance()
                + " cost: " + (end - start) / 1000_000 + " ms");
    }
}
```

某次执行结果

```shelll
330 cost: 306 ms 
```

## 为什么不安全 

withdraw 方法

```java
@Override
public void withdraw(Integer amount) {
    this.balance -= amount;
}
```

```shell
ALOAD 0 // <- this
ALOAD 0
GETFIELD cn/itcast/AccountUnsafe.balance : Ljava/lang/Integer; // <- this.balance
INVOKEVIRTUAL java/lang/Integer.intValue ()I // 拆箱
ALOAD 1 // <- amount
INVOKEVIRTUAL java/lang/Integer.intValue ()I // 拆箱
ISUB // 减法
INVOKESTATIC java/lang/Integer.valueOf (I)Ljava/lang/Integer; // 结果装箱
PUTFIELD cn/itcast/AccountUnsafe.balance : Ljava/lang/Integer; // -> this.balance
```

多线程执行流程

```shell
ALOAD 0 // thread-0 <- this 
ALOAD 0 
GETFIELD cn/itcast/AccountUnsafe.balance // thread-0 <- this.balance 
INVOKEVIRTUAL java/lang/Integer.intValue // thread-0 拆箱
ALOAD 1 // thread-0 <- amount 
INVOKEVIRTUAL java/lang/Integer.intValue // thread-0 拆箱
ISUB // thread-0 减法
INVOKESTATIC java/lang/Integer.valueOf // thread-0 结果装箱
PUTFIELD cn/itcast/AccountUnsafe.balance // thread-0 -> this.balance 

ALOAD 0 // thread-1 <- this 
ALOAD 0 
GETFIELD cn/itcast/AccountUnsafe.balance // thread-1 <- this.balance 
INVOKEVIRTUAL java/lang/Integer.intValue // thread-1 拆箱
ALOAD 1 // thread-1 <- amount 
INVOKEVIRTUAL java/lang/Integer.intValue // thread-1 拆箱
ISUB // thread-1 减法
INVOKESTATIC java/lang/Integer.valueOf // thread-1 结果装箱
PUTFIELD cn/itcast/AccountUnsafe.balance // thread-1 -> this.balance 
```

单核的指令交错；多核的指令交错

## 解决

- 给对象加锁

- 无锁：AtomicInteger

```java
package unlock;

import java.util.ArrayList;
import java.util.List;
import java.util.concurrent.atomic.AtomicInteger;

public class TestAccount {
    public static void main(String[] args) {
        Account account = new AccountSafe(10000);
        Account.demo(account);
    }
}

class AccountSafe implements Account {
    private AtomicInteger balance;

    public AccountSafe(Integer balance) {
        this.balance = new AtomicInteger(balance);
    }

    @Override
    public Integer getBalance() {
        return balance.get();
    }

    @Override
    public void withdraw(Integer amount) {
        while (true) {
            // 获取余额的最新值
            int prev = balance.get();
            // 把 prev 修改为 next  线程内完成的
            int next = prev - amount;
            // 把修改的余额，同步到主存中去。
            if (balance.compareAndSet(prev, next)) {
                // 失败就 break 进行下一次的尝试
                break;
            }
        }
        // 可以简化为下面的方法
        // balance.addAndGet(-1 * amount);
    }
}


interface Account {
    // 获取余额
    Integer getBalance();

    // 取款
    void withdraw(Integer amount);

    /**
     * 方法内会启动 1000 个线程，每个线程做 -10 元 的操作
     * 如果初始余额为 10000 那么正确的结果应当是 0
     */
    static void demo(Account account) {
        List<Thread> ts = new ArrayList<>();
        long start = System.nanoTime();
        for (int i = 0; i < 1000; i++) {
            ts.add(new Thread(() -> {
                account.withdraw(10);
            }));
        }
        ts.forEach(Thread::start);
        ts.forEach(t -> {
            try {
                t.join();
            } catch (InterruptedException e) {
                e.printStackTrace();
            }
        });
        long end = System.nanoTime();
        System.out.println(account.getBalance()
                + " cost: " + (end - start) / 1000_000 + " ms");
    }
}
```

执行测试代码

```java
public static void main(String[] args) {
 Account.demo(new AccountSafe(10000));
}
// 某次的执行结果 0 cost: 302 ms 
```



# CAS 与 volatile

前面看到的 AtomicInteger 的解决方法，内部并没有用锁来保护共享变量的线程安全。那么它是如何实现的呢？

```java
public void withdraw(Integer amount) {
    while (true) {
        // 需要不断尝试，直到成功为止
        while (true) {
            // 比如拿到了旧值 1000
            int prev = balance.get();
            // 在这个基础上 1000-10 = 990
            int next = prev - amount;
            /*
                 compareAndSet 正是做这个检查，在 set 前，先比较 prev 与当前值
                 - 不一致了，next 作废，返回 false 表示失败
                 比如，别的线程已经做了减法，当前值已经被减成了 990
                 那么本线程的这次 990 就作废了，进入 while 下次循环重试
                 - 一致，以 next 设置为新值，返回 true 表示成功
                 */
            if (balance.compareAndSet(prev, next)) {
                break;
            }
        }
    }
}
```

其中的关键是 compareAndSet，它的简称就是 CAS （也有 Compare And Swap 的说法），它必须是原子操作。

**注意** 其实 CAS 的底层是 lock cmpxchg 指令（X86 架构），在单核 CPU 和多核 CPU 下都能够保证【比较-交 换】的原子性。在多核状态下，某个核执行到带 lock 的指令时，CPU 会让总线锁住（或者锁缓存），当这个核把此指令执行完毕，再 开启总线。这个过程中不会被线程的调度机制所打断，保证了多个线程对内存操作的准确性，是原子 的。

